whohot/__init__.py
whohot/hello.py
whohot/cli/__init__.py
whohot/cli/config_manager.py
whohot/cli/main.py
whohot-0.1.0.dist-info/licenses/LICENSE
whohot-0.1.0.dist-info/METADATA
whohot-0.1.0.dist-info/WHEEL
whohot-0.1.0.dist-info/entry_points.txt
whohot-0.1.0.dist-info/top_level.txt
whohot-0.1.0.dist-info/RECORD
