Metadata-Version: 2.4
Name: whohot
Version: 0.1.0
Summary: A simple Python package for
Author-email: whillhill <ooooofish@126.com>
Maintainer-email: whillhill <ooooofish@126.com>
License: MIT
Project-URL: Homepage, https://github.com/whillhill/whohot
Project-URL: Repository, https://github.com/whillhill/whohot
Project-URL: Issues, https://github.com/whillhill/whohot/issues
Keywords: a2a,store,hello,example
Classifier: Development Status :: 3 - Alpha
Classifier: Intended Audience :: Developers
Classifier: License :: OSI Approved :: MIT License
Classifier: Programming Language :: Python :: 3
Classifier: Programming Language :: Python :: 3.8
Classifier: Programming Language :: Python :: 3.9
Classifier: Programming Language :: Python :: 3.10
Classifier: Programming Language :: Python :: 3.11
Classifier: Programming Language :: Python :: 3.12
Requires-Python: >=3.8
License-File: LICENSE
Dynamic: license-file
